Workbook
Name Slicer_MONTHS: #N/A

Sheet Raw_Data
A1: DATE | B1: MONTHS | C1: STUDENTS_REGISTERD | D1: REVENUE | E1: FUEL_EXPENSES | F1: OTHER_EXPENSES | G1: DEBTORS | H1: TOTAL_EXPENSES | I1: PROFIT | J1: GROWTH_RATE | K1: REVENUE PER STUDENT | L1: PROFIT MARGIN | M1: EXPENSE RATIO
A2: 31/1/25 | B2: JAN | C2: 17 | D2: 43500 | E2: 4450 | F2: 486 | G2: 4500 | H2: =E2+F2 -> 4936 | I2: =D2-H2 -> 38564 | K2: =D2/C2 -> 2558.8235 | L2: =I2/D2 -> 0.88652874 | M2: =H2/D2 -> 0.11347126
A3: 28/2/25 | B3: FEB | C3: 20 | D3: 49900 | E3: 6050 | F3: 177.5 | G3: 6500 | H3: =E3+F3 -> 6227.5 | I3: =D3-H3 -> 43672.5 | J3: =(D3-D2)/D2 -> 0.14712644 | K3: =D3/C3 -> 2495 | L3: =I3/D3 -> 0.8752004 | M3: =H3/D3 -> 0.1247996
A4: 31/3/25 | B4: MAR | C4: 10 | D4: 28900 | E4: 7000 | F4: 268.5 | G4: 5000 | H4: =E4+F4 -> 7268.5 | I4: =D4-H4 -> 21631.5 | J4: =(D4-D3)/D3 -> -0.42084168 | K4: =D4/C4 -> 2890 | L4: =I4/D4 -> 0.74849481 | M4: =H4/D4 -> 0.25150519
A5: 30/4/25 | B5: APR | C5: 17 | D5: 44900 | E5: 5300 | F5: 341 | G5: 2400 | H5: =E5+F5 -> 5641 | I5: =D5-H5 -> 39259 | J5: =(D5-D4)/D4 -> 0.55363322 | K5: =D5/C5 -> 2641.1765 | L5: =I5/D5 -> 0.87436526 | M5: =H5/D5 -> 0.12563474
A6: 30/5/25 | B6: MAY | C6: 21 | D6: 54700 | E6: 5700 | F6: 241 | G6: 2800 | H6: =E6+F6 -> 5941 | I6: =D6-H6 -> 48759 | J6: =(D6-D5)/D5 -> 0.21826281 | K6: =D6/C6 -> 2604.7619 | L6: =I6/D6 -> 0.8913894 | M6: =H6/D6 -> 0.1086106
A7: 30/6/25 | B7: JUN | C7: 18 | D7: 42900 | E7: 5300 | F7: 0 | G7: 6400 | H7: =E7+F7 -> 5300 | I7: =D7-H7 -> 37600 | J7: =(D7-D6)/D6 -> -0.21572212 | K7: =D7/C7 -> 2383.3333 | L7: =I7/D7 -> 0.87645688 | M7: =H7/D7 -> 0.12354312
A8: 31/7/25 | B8: JUL | C8: 13 | D8: 36700 | E8: 7000 | F8: 57 | G8: 200 | H8: =E8+F8 -> 7057 | I8: =D8-H8 -> 29643 | J8: =(D8-D7)/D7 -> -0.14452214 | K8: =D8/C8 -> 2823.0769 | L8: =I8/D8 -> 0.80771117 | M8: =H8/D8 -> 0.19228883
A9: 30/8/25 | B9: AUG | C9: 19 | D9: 40400 | E9: 5000 | F9: 86.5 | G9: 12400 | H9: =E9+F9 -> 5086.5 | I9: =D9-H9 -> 35313.5 | J9: =(D9-D8)/D8 -> 0.10081744 | K9: =D9/C9 -> 2126.3158 | L9: =I9/D9 -> 0.87409653 | M9: =H9/D9 -> 0.12590347
A10: 30/9/25 | B10: SEP | C10: 25 | D10: 56800 | E10: 4100 | F10: 144 | G10: 20900 | H10: =E10+F10 -> 4244 | I10: =D10-H10 -> 52556 | J10: =(D10-D9)/D9 -> 0.40594059 | K10: =D10/C10 -> 2272 | L10: =I10/D10 -> 0.92528169 | M10: =H10/D10 -> 0.07471831
A11: 31/10/25 | B11: OCT | C11: 27 | D11: 83600 | E11: 9000 | F11: 115 | G11: 19600 | H11: =E11+F11 -> 9115 | I11: =D11-H11 -> 74485 | J11: =(D11-D10)/D10 -> 0.47183099 | K11: =D11/C11 -> 3096.2963 | L11: =I11/D11 -> 0.8909689 | M11: =H11/D11 -> 0.1090311
A12: 30/11/25 | B12: NOV | C12: 19 | D12: 62200 | E12: 7000 | F12: 359.5 | G12: 12600 | H12: =E12+F12 -> 7359.5 | I12: =D12-H12 -> 54840.5 | J12: =(D12-D11)/D11 -> -0.25598086 | K12: =D12/C12 -> 3273.6842 | L12: =I12/D12 -> 0.88168006 | M12: =H12/D12 -> 0.11831994
A13: 31/12/25 | B13: DEC | C13: 7 | D13: 26200 | E13: 3300 | F13: 134 | G13: 7100 | H13: =E13+F13 -> 3434 | I13: =D13-H13 -> 22766 | J13: =(D13-D12)/D12 -> -0.57877814 | K13: =D13/C13 -> 3742.8571 | L13: =I13/D13 -> 0.8689313 | M13: =H13/D13 -> 0.1310687
D14: =SUM(D2:D13) -> 570700 | E14: =SUM(E2:E13) -> 69200 | F14: =SUM(F2:F13) -> 2410 | G14: =SUM(G2:G13) -> 100400 | H14: =SUM(H2:H13) -> 71610 | I14: =SUM(I2:I13) -> 499090

Sheet Dashboard_Data
A1: TOTAL_REVENUE | B1: TOTAL_STUDENTS | C1: TOTAL_EXPENSES | D1: TOTAL_PROFIT
A2: =SUM(Raw_Data!D2:D13) -> 570700 | B2: =SUM(Raw_Data!C2:C13) -> 213 | C2: =SUM(Raw_Data!H2:H13) -> 71610 | D2: =SUM(Raw_Data!I2:I13) -> 499090
A8: Expenses Type | B8: Amount
A9: Fuel | B9: =SUM(Raw_Data!E2:E13) -> 69200
A11: Other | B11: =SUM(Raw_Data!F2:F13) -> 2410

Sheet Dashboard
Z1: METRICS | AA1: VALUES
Z2: Total Revenue | AA2: =Dashboard_Data!A2 -> 570700
Z3: Total Students | AA3: =Dashboard_Data!B2 -> 213
Z4: Total Profits | AA4: =Dashboard_Data!D2 -> 499090
Z5: Profit Margin | AA5: =AA4/AA2 -> 0.87452252
